segmentation_models_3D/__init__.py
segmentation_models_3D/__version__.py
segmentation_models_3D/losses.py
segmentation_models_3D/metrics.py
segmentation_models_3D/utils.py
segmentation_models_3D/backbones/__init__.py
segmentation_models_3D/backbones/backbones_factory.py
segmentation_models_3D/backbones/inception_resnet_v2.py
segmentation_models_3D/backbones/inception_v3.py
segmentation_models_3D/base/__init__.py
segmentation_models_3D/base/functional.py
segmentation_models_3D/base/objects.py
segmentation_models_3D/models/__init__.py
segmentation_models_3D/models/_common_blocks.py
segmentation_models_3D/models/_utils.py
segmentation_models_3D/models/fpn.py
segmentation_models_3D/models/linknet.py
segmentation_models_3D/models/pspnet.py
segmentation_models_3D/models/unet.py
segmentation_models_3D-1.1.1.dist-info/LICENSE
segmentation_models_3D-1.1.1.dist-info/METADATA
segmentation_models_3D-1.1.1.dist-info/WHEEL
segmentation_models_3D-1.1.1.dist-info/top_level.txt
segmentation_models_3D-1.1.1.dist-info/RECORD
