Metadata-Version: 2.1
Name: segmentation-models-3D
Version: 1.1.1
Summary: Set of Keras models for segmentation of 3D volumes .
Home-page: https://github.com/ZFTurbo/segmentation_models_3D
Author: Roman Sol (ZFTurbo)
Author-email: UNKNOWN
License: UNKNOWN
Platform: UNKNOWN
Requires-Dist: keras (==3.3.3)
Requires-Dist: classification-models-3D (==1.1.0)
